<Scene xmlns:xsd="http://www.w3.org/2001/XMLSchema" xmlns:xsi="http://www.w3.org/2001/XMLSchema-instance" xmlns="http://mini.pw.edu.pl/mg1">
    <Point Name="KorpusPoint_0">
        <Position X="46.193588" Y="-9.253746" Z="15.000099"/>
    </Point>
    <Point Name="KorpusPoint_1">
        <Position X="46.39357" Y="-9.2537422" Z="15.000099"/>
    </Point>
    <Point Name="KorpusPoint_2">
        <Position X="46.39357" Y="-9.2537422" Z="15.000099"/>
    </Point>
    <Point Name="KorpusPoint_3">
        <Position X="46.39357" Y="-9.2537422" Z="15.000099"/>
    </Point>
    <Point Name="KorpusPoint_4">
        <Position X="46.39357" Y="-9.2537422" Z="15.000099"/>
    </Point>
    <Point Name="KorpusPoint_5">
        <Position X="46.39357" Y="-9.2537422" Z="15.000099"/>
    </Point>
    <Point Name="KorpusPoint_6">
        <Position X="46.39357" Y="-9.2537422" Z="15.000099"/>
    </Point>
    <Point Name="KorpusPoint_7">
        <Position X="46.39357" Y="-9.2537422" Z="15.000097"/>
    </Point>
    <Point Name="KorpusPoint_8">
        <Position X="46.39357" Y="-9.2537498" Z="15.000097"/>
    </Point>
    <Point Name="KorpusPoint_9">
        <Position X="46.39357" Y="-9.2537422" Z="15.000099"/>
    </Point>
    <Point Name="KorpusPoint_10">
        <Position X="46.39357" Y="-9.253746" Z="15.000099"/>
    </Point>
    <Point Name="KorpusPoint_11">
        <Position X="46.39357" Y="-9.2537498" Z="15.000097"/>
    </Point>
    <Point Name="KorpusPoint_12">
        <Position X="46.39357" Y="-9.2537422" Z="15.000099"/>
    </Point>
    <Point Name="KorpusPoint_13">
        <Position X="46.39357" Y="-9.2537422" Z="15.000099"/>
    </Point>
    <Point Name="KorpusPoint_14">
        <Position X="46.39357" Y="-9.2537498" Z="15.000099"/>
    </Point>
    <Point Name="KorpusPoint_15">
        <Position X="46.39357" Y="-9.2537498" Z="15.000099"/>
    </Point>
    <Point Name="KorpusPoint_16">
        <Position X="46.39357" Y="-9.2537422" Z="15.000099"/>
    </Point>
    <Point Name="KorpusPoint_17">
        <Position X="46.39357" Y="-9.2537422" Z="15.000099"/>
    </Point>
    <Point Name="KorpusPoint_18">
        <Position X="-32.421059" Y="76.168015" Z="15.000119"/>
    </Point>
    <Point Name="KorpusPoint_19">
        <Position X="-32.421379" Y="55.404976" Z="50.979797"/>
    </Point>
    <Point Name="KorpusPoint_20">
        <Position X="-32.421341" Y="-35.93235" Z="50.979759"/>
    </Point>
    <Point Name="KorpusPoint_21">
        <Position X="-32.421356" Y="-56.693569" Z="15.000096"/>
    </Point>
    <Point Name="KorpusPoint_22">
        <Position X="-32.421547" Y="-35.932266" Z="-20.979565"/>
    </Point>
    <Point Name="KorpusPoint_23">
        <Position X="-32.421486" Y="55.405045" Z="-20.979519"/>
    </Point>
    <Point Name="KorpusPoint_24">
        <Position X="-73.409409" Y="1.4318476" Z="15.000104"/>
    </Point>
    <Point Name="KorpusPoint_25">
        <Position X="-73.409409" Y="1.4318476" Z="15.000104"/>
    </Point>
    <Point Name="KorpusPoint_26">
        <Position X="-73.409409" Y="1.4318476" Z="15.000104"/>
    </Point>
    <Point Name="KorpusPoint_27">
        <Position X="-73.409409" Y="1.4318476" Z="15.000104"/>
    </Point>
    <Point Name="KorpusPoint_28">
        <Position X="-73.409409" Y="1.4318476" Z="15.000104"/>
    </Point>
    <Point Name="KorpusPoint_29">
        <Position X="-73.409409" Y="1.4318476" Z="15.000104"/>
    </Point>
    <Point Name="KorpusPoint_30">
        <Position X="-73.409393" Y="1.4318476" Z="15.000104"/>
    </Point>
    <Point Name="KorpusPoint_31">
        <Position X="-73.409393" Y="1.4318476" Z="15.000104"/>
    </Point>
    <Point Name="KorpusPoint_32">
        <Position X="-73.409393" Y="1.4318476" Z="15.000104"/>
    </Point>
    <Point Name="KorpusPoint_33">
        <Position X="-73.409393" Y="1.4318476" Z="15.000104"/>
    </Point>
    <Point Name="KorpusPoint_34">
        <Position X="-73.409393" Y="1.4318476" Z="15.000104"/>
    </Point>
    <Point Name="KorpusPoint_35">
        <Position X="-73.409393" Y="1.4318476" Z="15.000104"/>
    </Point>
    <Point Name="KorpusPoint_36">
        <Position X="-73.409393" Y="1.4318476" Z="15.000104"/>
    </Point>
    <Point Name="KorpusPoint_37">
        <Position X="-73.409393" Y="1.4318476" Z="15.000104"/>
    </Point>
    <Point Name="KorpusPoint_38">
        <Position X="-73.409393" Y="1.4318476" Z="15.000104"/>
    </Point>
    <Point Name="KorpusPoint_39">
        <Position X="-73.409393" Y="1.4318476" Z="15.000104"/>
    </Point>
    <Point Name="KorpusPoint_40">
        <Position X="-73.409393" Y="1.4318476" Z="15.000104"/>
    </Point>
    <Point Name="KorpusPoint_41">
        <Position X="-73.409393" Y="1.4318476" Z="15.000104"/>
    </Point>
    <Point Name="LoopPoint_0">
        <Position X="-31.620438" Y="27.87928" Z="14.999978"/>
    </Point>
    <Point Name="LoopPoint_1">
        <Position X="-35.148308" Y="25.674805" Z="29.837734"/>
    </Point>
    <Point Name="LoopPoint_2">
        <Position X="-38.676231" Y="23.47031" Z="14.999975"/>
    </Point>
    <Point Name="LoopPoint_3">
        <Position X="-35.148293" Y="25.67482" Z="0.16221905"/>
    </Point>
    <Point Name="LoopPoint_4">
        <Position X="-37.531136" Y="37.338387" Z="14.999975"/>
    </Point>
    <Point Name="LoopPoint_5">
        <Position X="-41.059021" Y="35.133919" Z="29.837734"/>
    </Point>
    <Point Name="LoopPoint_6">
        <Position X="-44.586937" Y="32.929432" Z="14.999975"/>
    </Point>
    <Point Name="LoopPoint_7">
        <Position X="-41.059013" Y="35.133907" Z="0.16221619"/>
    </Point>
    <Point Name="LoopPoint_8">
        <Position X="-44.572067" Y="45.466141" Z="14.999968"/>
    </Point>
    <Point Name="LoopPoint_9">
        <Position X="-48.099953" Y="43.261681" Z="29.837734"/>
    </Point>
    <Point Name="LoopPoint_10">
        <Position X="-51.627846" Y="41.057198" Z="14.999969"/>
    </Point>
    <Point Name="LoopPoint_11">
        <Position X="-48.099968" Y="43.261673" Z="0.16221523"/>
    </Point>
    <Point Name="LoopPoint_12">
        <Position X="-57.198765" Y="54.298767" Z="14.999793"/>
    </Point>
    <Point Name="LoopPoint_13">
        <Position X="-56.558716" Y="47.723518" Z="29.83757"/>
    </Point>
    <Point Name="LoopPoint_14">
        <Position X="-55.918694" Y="41.148293" Z="14.999793"/>
    </Point>
    <Point Name="LoopPoint_15">
        <Position X="-62.325531" Y="44.120064" Z="0.16204071"/>
    </Point>
    <Point Name="LoopPoint_16">
        <Position X="-80.364487" Y="32.344967" Z="14.999802"/>
    </Point>
    <Point Name="LoopPoint_17">
        <Position X="-72.152695" Y="30.748756" Z="23.902466"/>
    </Point>
    <Point Name="LoopPoint_18">
        <Position X="-63.940903" Y="29.15255" Z="14.999804"/>
    </Point>
    <Point Name="LoopPoint_19">
        <Position X="-72.15271" Y="30.748756" Z="6.097146"/>
    </Point>
    <Point Name="LoopPoint_20">
        <Position X="-58.84972" Y="6.615119" Z="14.731441"/>
    </Point>
    <Point Name="LoopPoint_21">
        <Position X="-53.817093" Y="10.017881" Z="23.899677"/>
    </Point>
    <Point Name="LoopPoint_22">
        <Position X="-48.695496" Y="13.63238" Z="15.268519"/>
    </Point>
    <Point Name="LoopPoint_23">
        <Position X="-53.728065" Y="10.229616" Z="6.1002913"/>
    </Point>
    <Point Name="LoopPoint_24">
        <Position X="-52.692451" Y="-2.3538404" Z="14.99998"/>
    </Point>
    <Point Name="LoopPoint_25">
        <Position X="-50.575722" Y="-1.0311642" Z="23.902637"/>
    </Point>
    <Point Name="LoopPoint_26">
        <Position X="-48.458984" Y="0.29151717" Z="14.999979"/>
    </Point>
    <Point Name="LoopPoint_27">
        <Position X="-50.575722" Y="-1.0311565" Z="6.0973234"/>
    </Point>
    <Point Name="TailPoint_0">
        <Position X="83.084854" Y="-57.244038" Z="14.999988"/>
    </Point>
    <Point Name="TailPoint_1">
        <Position X="59.992607" Y="-19.48605" Z="15.000066"/>
    </Point>
    <Point Name="TailPoint_2">
        <Position X="59.992599" Y="6.5539589" Z="14.999926"/>
    </Point>
    <Point Name="TailPoint_3">
        <Position X="86.365921" Y="36.499954" Z="15"/>
    </Point>
    <Point Name="TailPoint_4">
        <Position X="59.992599" Y="6.553957" Z="14.999927"/>
    </Point>
    <Point Name="TailPoint_5">
        <Position X="59.992607" Y="-19.486057" Z="15.000066"/>
    </Point>
    <Point Name="TailPoint_6">
        <Position X="71.710602" Y="-57.244038" Z="14.999989"/>
    </Point>
    <Point Name="TailPoint_7">
        <Position X="59.992607" Y="-19.48605" Z="14.99993"/>
    </Point>
    <Point Name="TailPoint_8">
        <Position X="59.992599" Y="6.5539608" Z="14.999926"/>
    </Point>
    <Point Name="TailPoint_9">
        <Position X="74.991653" Y="36.499954" Z="15.000001"/>
    </Point>
    <Point Name="TailPoint_10">
        <Position X="59.992599" Y="6.5539589" Z="14.999926"/>
    </Point>
    <Point Name="TailPoint_11">
        <Position X="59.992607" Y="-19.48605" Z="14.99993"/>
    </Point>
    <Point Name="TailPoint_12">
        <Position X="60.336349" Y="-57.244038" Z="14.99999"/>
    </Point>
    <Point Name="TailPoint_13">
        <Position X="59.992607" Y="-19.486057" Z="14.99993"/>
    </Point>
    <Point Name="TailPoint_14">
        <Position X="59.992607" Y="6.5539589" Z="14.999927"/>
    </Point>
    <Point Name="TailPoint_15">
        <Position X="63.617386" Y="36.499962" Z="15.000002"/>
    </Point>
    <Point Name="TailPoint_16">
        <Position X="59.992607" Y="6.5539589" Z="14.999927"/>
    </Point>
    <Point Name="TailPoint_17">
        <Position X="59.992607" Y="-19.48605" Z="14.99993"/>
    </Point>
    <Point Name="TailPoint_18">
        <Position X="52.024376" Y="-32.506027" Z="14.999932"/>
    </Point>
    <Point Name="TailPoint_19">
        <Position X="52.024376" Y="-19.486046" Z="5.7590919"/>
    </Point>
    <Point Name="TailPoint_20">
        <Position X="50.071373" Y="-16.231045" Z="5.7592292"/>
    </Point>
    <Point Name="TailPoint_21">
        <Position X="52.024384" Y="19.573959" Z="14.999925"/>
    </Point>
    <Point Name="TailPoint_22">
        <Position X="50.071373" Y="-16.231041" Z="24.240894"/>
    </Point>
    <Point Name="TailPoint_23">
        <Position X="52.024384" Y="-19.48605" Z="24.240757"/>
    </Point>
    <Point Name="TailPoint_24">
        <Position X="43.899887" Y="-32.506027" Z="14.999933"/>
    </Point>
    <Point Name="TailPoint_25">
        <Position X="43.899895" Y="-19.486042" Z="5.7590904"/>
    </Point>
    <Point Name="TailPoint_26">
        <Position X="43.899895" Y="6.5539551" Z="5.7590866"/>
    </Point>
    <Point Name="TailPoint_27">
        <Position X="43.899895" Y="19.573959" Z="14.999926"/>
    </Point>
    <Point Name="TailPoint_28">
        <Position X="43.899895" Y="6.5539589" Z="24.240757"/>
    </Point>
    <Point Name="TailPoint_29">
        <Position X="43.899895" Y="-19.48605" Z="24.240761"/>
    </Point>
    <Point Name="TailPoint_30">
        <Position X="35.775414" Y="-32.506027" Z="14.999934"/>
    </Point>
    <Point Name="TailPoint_31">
        <Position X="35.775414" Y="-19.486042" Z="5.7590933"/>
    </Point>
    <Point Name="TailPoint_32">
        <Position X="35.775406" Y="6.553957" Z="5.7590876"/>
    </Point>
    <Point Name="TailPoint_33">
        <Position X="35.775406" Y="19.573956" Z="14.999927"/>
    </Point>
    <Point Name="TailPoint_34">
        <Position X="35.775406" Y="6.5539589" Z="24.240757"/>
    </Point>
    <Point Name="TailPoint_35">
        <Position X="35.775406" Y="-19.486046" Z="24.240761"/>
    </Point>
    <Point Name="TailPoint_36">
        <Position X="19.526455" Y="-6.4660292" Z="14.999931"/>
    </Point>
    <Point Name="TailPoint_37">
        <Position X="19.526459" Y="-6.4660292" Z="14.999931"/>
    </Point>
    <Point Name="TailPoint_38">
        <Position X="19.526455" Y="-6.4660292" Z="14.999931"/>
    </Point>
    <Point Name="TailPoint_39">
        <Position X="19.526455" Y="-6.4660254" Z="14.999931"/>
    </Point>
    <Point Name="TailPoint_40">
        <Position X="19.526455" Y="-6.4660292" Z="14.999931"/>
    </Point>
    <Point Name="TailPoint_41">
        <Position X="19.526459" Y="-6.4660292" Z="14.999931"/>
    </Point>
    <Point Name="TailPoint_42">
        <Position X="19.526459" Y="-6.4660292" Z="14.999931"/>
    </Point>
    <Point Name="TailPoint_43">
        <Position X="19.526459" Y="-6.4660254" Z="14.999931"/>
    </Point>
    <Point Name="TailPoint_44">
        <Position X="19.526459" Y="-6.4660292" Z="14.999931"/>
    </Point>
    <Point Name="TailPoint_45">
        <Position X="19.526459" Y="-6.4660292" Z="14.999931"/>
    </Point>
    <Point Name="TailPoint_46">
        <Position X="19.526459" Y="-6.4660292" Z="14.999931"/>
    </Point>
    <Point Name="TailPoint_47">
        <Position X="19.526459" Y="-6.4660292" Z="14.999931"/>
    </Point>
    <Point Name="TailPoint_48">
        <Position X="19.526459" Y="-6.4660292" Z="14.999931"/>
    </Point>
    <Point Name="TailPoint_49">
        <Position X="19.526459" Y="-6.4660254" Z="14.999931"/>
    </Point>
    <Point Name="TailPoint_50">
        <Position X="19.526459" Y="-6.4660292" Z="14.999931"/>
    </Point>
    <Point Name="TailPoint_51">
        <Position X="19.526455" Y="-6.4660292" Z="14.999931"/>
    </Point>
    <Point Name="TailPoint_52">
        <Position X="19.526455" Y="-6.4660254" Z="14.999931"/>
    </Point>
    <Point Name="TailPoint_53">
        <Position X="19.526455" Y="-6.4660292" Z="14.999931"/>
    </Point>
    <Point Name="TopFinPoint_0">
        <Position X="-28.14385" Y="38.856827" Z="14.999924"/>
    </Point>
    <Point Name="TopFinPoint_1">
        <Position X="-14.152933" Y="30.160671" Z="14.999922"/>
    </Point>
    <Point Name="TopFinPoint_2">
        <Position X="-6.4668541" Y="22.132088" Z="14.999922"/>
    </Point>
    <Point Name="TopFinPoint_3">
        <Position X="-0.69907093" Y="21.797096" Z="14.999921"/>
    </Point>
    <Point Name="TopFinPoint_4">
        <Position X="2.3944776" Y="19.873943" Z="14.999924"/>
    </Point>
    <Point Name="TopFinPoint_5">
        <Position X="6.699213" Y="17.19804" Z="14.999924"/>
    </Point>
    <Point Name="TopFinPoint_6">
        <Position X="14.6351" Y="12.265032" Z="14.999923"/>
    </Point>
    <Point Name="TopFinPoint_7">
        <Position X="18.945683" Y="9.5853939" Z="14.999922"/>
    </Point>
    <Point Name="TopFinPoint_8">
        <Position X="22.644699" Y="7.2858219" Z="14.999922"/>
    </Point>
    <Point Name="TopFinPoint_9">
        <Position X="25.738588" Y="5.3655128" Z="14.999922"/>
    </Point>
    <Point Name="TopFinPoint_10">
        <Position X="-28.143232" Y="38.859802" Z="14.999924"/>
    </Point>
    <Point Name="TopFinPoint_11">
        <Position X="-13.618814" Y="39.61908" Z="1.0895205"/>
    </Point>
    <Point Name="TopFinPoint_12">
        <Position X="-6.8920422" Y="35.437958" Z="-2.5392685"/>
    </Point>
    <Point Name="TopFinPoint_13">
        <Position X="-0.16507792" Y="31.256187" Z="-2.5392685"/>
    </Point>
    <Point Name="TopFinPoint_14">
        <Position X="2.7778797" Y="26.459854" Z="-2.5392685"/>
    </Point>
    <Point Name="TopFinPoint_15">
        <Position X="7.8365307" Y="26.281956" Z="-2.5392704"/>
    </Point>
    <Point Name="TopFinPoint_16">
        <Position X="15.169356" Y="21.723606" Z="-2.5392704"/>
    </Point>
    <Point Name="TopFinPoint_17">
        <Position X="19.479858" Y="19.044102" Z="-2.539278"/>
    </Point>
    <Point Name="TopFinPoint_18">
        <Position X="23.179012" Y="16.744816" Z="-2.5392723"/>
    </Point>
    <Point Name="TopFinPoint_19">
        <Position X="25.738676" Y="5.365551" Z="14.999922"/>
    </Point>
    <Point Name="TopFinPoint_20">
        <Position X="-28.143469" Y="38.859741" Z="14.999924"/>
    </Point>
    <Point Name="TopFinPoint_21">
        <Position X="-14.632174" Y="31.7924" Z="-2.5392685"/>
    </Point>
    <Point Name="TopFinPoint_22">
        <Position X="-6.7183666" Y="38.512192" Z="-2.5392609"/>
    </Point>
    <Point Name="TopFinPoint_23">
        <Position X="-0.03159368" Y="33.621338" Z="-2.5392685"/>
    </Point>
    <Point Name="TopFinPoint_24">
        <Position X="2.6616402" Y="24.606369" Z="-2.5392685"/>
    </Point>
    <Point Name="TopFinPoint_25">
        <Position X="8.1303825" Y="31.48484" Z="-2.5392704"/>
    </Point>
    <Point Name="TopFinPoint_26">
        <Position X="16.398312" Y="28.395947" Z="-2.5392704"/>
    </Point>
    <Point Name="TopFinPoint_27">
        <Position X="20.054195" Y="29.212994" Z="-2.5392704"/>
    </Point>
    <Point Name="TopFinPoint_28">
        <Position X="22.831772" Y="10.59692" Z="-2.5392723"/>
    </Point>
    <Point Name="TopFinPoint_29">
        <Position X="25.73868" Y="5.3655567" Z="14.999922"/>
    </Point>
    <Point Name="TopFinPoint_30">
        <Position X="-28.143454" Y="38.859756" Z="14.999924"/>
    </Point>
    <Point Name="TopFinPoint_31">
        <Position X="-13.632204" Y="39.383049" Z="14.999922"/>
    </Point>
    <Point Name="TopFinPoint_32">
        <Position X="-6.1842113" Y="47.971092" Z="14.999922"/>
    </Point>
    <Point Name="TopFinPoint_33">
        <Position X="0.50254905" Y="43.080101" Z="14.999921"/>
    </Point>
    <Point Name="TopFinPoint_34">
        <Position X="4.7011089" Y="39.806152" Z="14.999921"/>
    </Point>
    <Point Name="TopFinPoint_35">
        <Position X="8.6645107" Y="40.943771" Z="14.99992"/>
    </Point>
    <Point Name="TopFinPoint_36">
        <Position X="16.237659" Y="40.641701" Z="14.99992"/>
    </Point>
    <Point Name="TopFinPoint_37">
        <Position X="20.588333" Y="38.671982" Z="14.999919"/>
    </Point>
    <Point Name="TopFinPoint_38">
        <Position X="23.366018" Y="20.055801" Z="14.999922"/>
    </Point>
    <Point Name="TopFinPoint_39">
        <Position X="25.738676" Y="5.3655586" Z="14.999922"/>
    </Point>
    <Point Name="TopFinPoint_40">
        <Position X="-28.14385" Y="38.856827" Z="14.999924"/>
    </Point>
    <Point Name="TopFinPoint_41">
        <Position X="-14.152925" Y="30.160671" Z="14.999922"/>
    </Point>
    <Point Name="TopFinPoint_42">
        <Position X="-6.4668617" Y="22.132088" Z="14.999922"/>
    </Point>
    <Point Name="TopFinPoint_43">
        <Position X="-0.69907093" Y="21.797092" Z="14.999924"/>
    </Point>
    <Point Name="TopFinPoint_44">
        <Position X="2.3944795" Y="19.873943" Z="14.999924"/>
    </Point>
    <Point Name="TopFinPoint_45">
        <Position X="6.6992111" Y="17.19804" Z="14.999924"/>
    </Point>
    <Point Name="TopFinPoint_46">
        <Position X="14.6351" Y="12.265032" Z="14.999923"/>
    </Point>
    <Point Name="TopFinPoint_47">
        <Position X="18.945683" Y="9.5853958" Z="14.999922"/>
    </Point>
    <Point Name="TopFinPoint_48">
        <Position X="22.644699" Y="7.2858219" Z="14.999922"/>
    </Point>
    <Point Name="TopFinPoint_49">
        <Position X="25.738585" Y="5.3655128" Z="14.999922"/>
    </Point>
    <Point Name="TopFinPoint_50">
        <Position X="-28.14324" Y="38.859795" Z="14.999924"/>
    </Point>
    <Point Name="TopFinPoint_51">
        <Position X="-13.61882" Y="39.61908" Z="28.910324"/>
    </Point>
    <Point Name="TopFinPoint_52">
        <Position X="-6.8920507" Y="35.437958" Z="32.539135"/>
    </Point>
    <Point Name="TopFinPoint_53">
        <Position X="-0.1650784" Y="31.256187" Z="32.539143"/>
    </Point>
    <Point Name="TopFinPoint_54">
        <Position X="2.7778847" Y="26.459854" Z="32.539131"/>
    </Point>
    <Point Name="TopFinPoint_55">
        <Position X="7.8365335" Y="26.281956" Z="32.539135"/>
    </Point>
    <Point Name="TopFinPoint_56">
        <Position X="15.16936" Y="21.723606" Z="32.539135"/>
    </Point>
    <Point Name="TopFinPoint_57">
        <Position X="19.479862" Y="19.044102" Z="32.539139"/>
    </Point>
    <Point Name="TopFinPoint_58">
        <Position X="23.179012" Y="16.744816" Z="32.539131"/>
    </Point>
    <Point Name="TopFinPoint_59">
        <Position X="25.738672" Y="5.365551" Z="14.999922"/>
    </Point>
    <Point Name="TopFinPoint_60">
        <Position X="-28.143454" Y="38.859749" Z="14.999924"/>
    </Point>
    <Point Name="TopFinPoint_61">
        <Position X="-14.632179" Y="31.7924" Z="32.539131"/>
    </Point>
    <Point Name="TopFinPoint_62">
        <Position X="-6.7183752" Y="38.512192" Z="32.539112"/>
    </Point>
    <Point Name="TopFinPoint_63">
        <Position X="-0.03159821" Y="33.621338" Z="32.539139"/>
    </Point>
    <Point Name="TopFinPoint_64">
        <Position X="2.6616414" Y="24.606365" Z="32.539135"/>
    </Point>
    <Point Name="TopFinPoint_65">
        <Position X="8.1303854" Y="31.48484" Z="32.539135"/>
    </Point>
    <Point Name="TopFinPoint_66">
        <Position X="16.398315" Y="28.395947" Z="32.539143"/>
    </Point>
    <Point Name="TopFinPoint_67">
        <Position X="20.054199" Y="29.212994" Z="32.539139"/>
    </Point>
    <Point Name="TopFinPoint_68">
        <Position X="22.831776" Y="10.596922" Z="32.539131"/>
    </Point>
    <Point Name="TopFinPoint_69">
        <Position X="25.73868" Y="5.3655548" Z="14.999922"/>
    </Point>
    <Point Name="BottomFinPoint_0">
        <Position X="21.062332" Y="-17.015049" Z="14.999919"/>
    </Point>
    <Point Name="BottomFinPoint_1">
        <Position X="10.235915" Y="-20.984814" Z="14.99992"/>
    </Point>
    <Point Name="BottomFinPoint_2">
        <Position X="2.4948671" Y="-21.764492" Z="14.999921"/>
    </Point>
    <Point Name="BottomFinPoint_3">
        <Position X="-0.17562008" Y="-24.801651" Z="14.999921"/>
    </Point>
    <Point Name="BottomFinPoint_4">
        <Position X="-2.5696516" Y="-25.679276" Z="14.999921"/>
    </Point>
    <Point Name="BottomFinPoint_5">
        <Position X="-5.900888" Y="-26.900585" Z="14.999922"/>
    </Point>
    <Point Name="BottomFinPoint_6">
        <Position X="-12.042027" Y="-29.152122" Z="14.999922"/>
    </Point>
    <Point Name="BottomFinPoint_7">
        <Position X="-15.377848" Y="-30.375053" Z="14.999923"/>
    </Point>
    <Point Name="BottomFinPoint_8">
        <Position X="-18.240446" Y="-31.424423" Z="14.999923"/>
    </Point>
    <Point Name="BottomFinPoint_9">
        <Position X="-20.633078" Y="-32.303467" Z="14.999923"/>
    </Point>
    <Point Name="BottomFinPoint_10">
        <Position X="21.063709" Y="-17.016666" Z="14.999919"/>
    </Point>
    <Point Name="BottomFinPoint_11">
        <Position X="15.223062" Y="-25.355621" Z="8.0447226"/>
    </Point>
    <Point Name="BottomFinPoint_12">
        <Position X="10.017724" Y="-27.264271" Z="6.2303228"/>
    </Point>
    <Point Name="BottomFinPoint_13">
        <Position X="4.8119516" Y="-29.172726" Z="6.2303252"/>
    </Point>
    <Point Name="BottomFinPoint_14">
        <Position X="0.89795297" Y="-28.72905" Z="6.2303257"/>
    </Point>
    <Point Name="BottomFinPoint_15">
        <Position X="-1.380266" Y="-31.442776" Z="6.2303262"/>
    </Point>
    <Point Name="BottomFinPoint_16">
        <Position X="-7.0548639" Y="-33.523148" Z="6.2303267"/>
    </Point>
    <Point Name="BottomFinPoint_17">
        <Position X="-10.390559" Y="-34.746086" Z="6.2303267"/>
    </Point>
    <Point Name="BottomFinPoint_18">
        <Position X="-13.25306" Y="-35.79567" Z="6.2303271"/>
    </Point>
    <Point Name="BottomFinPoint_19">
        <Position X="-20.633085" Y="-32.303543" Z="14.999923"/>
    </Point>
    <Point Name="BottomFinPoint_20">
        <Position X="21.06377" Y="-17.016521" Z="14.999919"/>
    </Point>
    <Point Name="BottomFinPoint_21">
        <Position X="11.342525" Y="-21.423656" Z="6.2303209"/>
    </Point>
    <Point Name="BottomFinPoint_22">
        <Position X="11.63865" Y="-28.684959" Z="6.2303305"/>
    </Point>
    <Point Name="BottomFinPoint_23">
        <Position X="6.059062" Y="-30.265652" Z="6.2303252"/>
    </Point>
    <Point Name="BottomFinPoint_24">
        <Position X="-0.074351788" Y="-27.866146" Z="6.2303257"/>
    </Point>
    <Point Name="BottomFinPoint_25">
        <Position X="1.3630372" Y="-33.84713" Z="6.2303276"/>
    </Point>
    <Point Name="BottomFinPoint_26">
        <Position X="-3.9039869" Y="-37.076591" Z="6.2303281"/>
    </Point>
    <Point Name="BottomFinPoint_27">
        <Position X="-5.0288496" Y="-39.44532" Z="6.2303281"/>
    </Point>
    <Point Name="BottomFinPoint_28">
        <Position X="-16.494654" Y="-32.954605" Z="6.2303271"/>
    </Point>
    <Point Name="BottomFinPoint_29">
        <Position X="-20.633093" Y="-32.303543" Z="14.999923"/>
    </Point>
    <Point Name="BottomFinPoint_30">
        <Position X="21.063778" Y="-17.016521" Z="14.999919"/>
    </Point>
    <Point Name="BottomFinPoint_31">
        <Position X="15.098639" Y="-25.246529" Z="14.99992"/>
    </Point>
    <Point Name="BottomFinPoint_32">
        <Position X="16.626049" Y="-33.056053" Z="14.99992"/>
    </Point>
    <Point Name="BottomFinPoint_33">
        <Position X="11.046391" Y="-34.636688" Z="14.99992"/>
    </Point>
    <Point Name="BottomFinPoint_34">
        <Position X="7.4310322" Y="-35.541702" Z="14.99992"/>
    </Point>
    <Point Name="BottomFinPoint_35">
        <Position X="6.3504696" Y="-38.218208" Z="14.999926"/>
    </Point>
    <Point Name="BottomFinPoint_36">
        <Position X="2.9201007" Y="-42.265411" Z="14.999926"/>
    </Point>
    <Point Name="BottomFinPoint_37">
        <Position X="-0.041384459" Y="-43.816406" Z="14.999926"/>
    </Point>
    <Point Name="BottomFinPoint_38">
        <Position X="-11.507287" Y="-37.325729" Z="14.999922"/>
    </Point>
    <Point Name="BottomFinPoint_39">
        <Position X="-20.633085" Y="-32.303543" Z="14.999923"/>
    </Point>
    <Point Name="BottomFinPoint_40">
        <Position X="21.062332" Y="-17.015041" Z="14.999919"/>
    </Point>
    <Point Name="BottomFinPoint_41">
        <Position X="10.235915" Y="-20.984806" Z="14.99992"/>
    </Point>
    <Point Name="BottomFinPoint_42">
        <Position X="2.4948671" Y="-21.764492" Z="14.999921"/>
    </Point>
    <Point Name="BottomFinPoint_43">
        <Position X="-0.17562008" Y="-24.801659" Z="14.999921"/>
    </Point>
    <Point Name="BottomFinPoint_44">
        <Position X="-2.5696516" Y="-25.679283" Z="14.999921"/>
    </Point>
    <Point Name="BottomFinPoint_45">
        <Position X="-5.9008803" Y="-26.900589" Z="14.999922"/>
    </Point>
    <Point Name="BottomFinPoint_46">
        <Position X="-12.042039" Y="-29.152134" Z="14.999922"/>
    </Point>
    <Point Name="BottomFinPoint_47">
        <Position X="-15.377863" Y="-30.375065" Z="14.999923"/>
    </Point>
    <Point Name="BottomFinPoint_48">
        <Position X="-18.240454" Y="-31.424446" Z="14.999923"/>
    </Point>
    <Point Name="BottomFinPoint_49">
        <Position X="-20.633062" Y="-32.303486" Z="14.999923"/>
    </Point>
    <Point Name="BottomFinPoint_50">
        <Position X="21.063709" Y="-17.016655" Z="14.999919"/>
    </Point>
    <Point Name="BottomFinPoint_51">
        <Position X="15.223063" Y="-25.355637" Z="21.95512"/>
    </Point>
    <Point Name="BottomFinPoint_52">
        <Position X="10.017724" Y="-27.264278" Z="23.76952"/>
    </Point>
    <Point Name="BottomFinPoint_53">
        <Position X="4.811955" Y="-29.172729" Z="23.76952"/>
    </Point>
    <Point Name="BottomFinPoint_54">
        <Position X="0.8979544" Y="-28.729046" Z="23.76952"/>
    </Point>
    <Point Name="BottomFinPoint_55">
        <Position X="-1.3802645" Y="-31.442776" Z="23.769524"/>
    </Point>
    <Point Name="BottomFinPoint_56">
        <Position X="-7.0548658" Y="-33.523159" Z="23.769524"/>
    </Point>
    <Point Name="BottomFinPoint_57">
        <Position X="-10.390561" Y="-34.746094" Z="23.769527"/>
    </Point>
    <Point Name="BottomFinPoint_58">
        <Position X="-13.253058" Y="-35.79567" Z="23.769527"/>
    </Point>
    <Point Name="BottomFinPoint_59">
        <Position X="-20.633085" Y="-32.303555" Z="14.999923"/>
    </Point>
    <Point Name="BottomFinPoint_60">
        <Position X="21.063774" Y="-17.016514" Z="14.999919"/>
    </Point>
    <Point Name="BottomFinPoint_61">
        <Position X="11.342526" Y="-21.423664" Z="23.76952"/>
    </Point>
    <Point Name="BottomFinPoint_62">
        <Position X="11.638652" Y="-28.684959" Z="23.769512"/>
    </Point>
    <Point Name="BottomFinPoint_63">
        <Position X="6.0590639" Y="-30.265652" Z="23.76952"/>
    </Point>
    <Point Name="BottomFinPoint_64">
        <Position X="-0.074346542" Y="-27.866154" Z="23.769524"/>
    </Point>
    <Point Name="BottomFinPoint_65">
        <Position X="1.3630425" Y="-33.847134" Z="23.76952"/>
    </Point>
    <Point Name="BottomFinPoint_66">
        <Position X="-3.903985" Y="-37.076591" Z="23.769524"/>
    </Point>
    <Point Name="BottomFinPoint_67">
        <Position X="-5.0288477" Y="-39.445313" Z="23.769524"/>
    </Point>
    <Point Name="BottomFinPoint_68">
        <Position X="-16.494646" Y="-32.954617" Z="23.769527"/>
    </Point>
    <Point Name="BottomFinPoint_69">
        <Position X="-20.633093" Y="-32.303547" Z="14.999923"/>
    </Point>
    <PatchC0 Name="TopFin" ShowControlPolygon="false" RowSlices="5" ColumnSlices="5" WrapDirection="None">
        <Points>
            <PointRef Name="TopFinPoint_0" Row="0" Column="0"/>
            <PointRef Name="TopFinPoint_1" Row="0" Column="1"/>
            <PointRef Name="TopFinPoint_2" Row="0" Column="2"/>
            <PointRef Name="TopFinPoint_3" Row="0" Column="3"/>
            <PointRef Name="TopFinPoint_4" Row="0" Column="4"/>
            <PointRef Name="TopFinPoint_5" Row="0" Column="5"/>
            <PointRef Name="TopFinPoint_6" Row="0" Column="6"/>
            <PointRef Name="TopFinPoint_7" Row="0" Column="7"/>
            <PointRef Name="TopFinPoint_8" Row="0" Column="8"/>
            <PointRef Name="TopFinPoint_9" Row="0" Column="9"/>
            <PointRef Name="TopFinPoint_10" Row="1" Column="0"/>
            <PointRef Name="TopFinPoint_11" Row="1" Column="1"/>
            <PointRef Name="TopFinPoint_12" Row="1" Column="2"/>
            <PointRef Name="TopFinPoint_13" Row="1" Column="3"/>
            <PointRef Name="TopFinPoint_14" Row="1" Column="4"/>
            <PointRef Name="TopFinPoint_15" Row="1" Column="5"/>
            <PointRef Name="TopFinPoint_16" Row="1" Column="6"/>
            <PointRef Name="TopFinPoint_17" Row="1" Column="7"/>
            <PointRef Name="TopFinPoint_18" Row="1" Column="8"/>
            <PointRef Name="TopFinPoint_19" Row="1" Column="9"/>
            <PointRef Name="TopFinPoint_20" Row="2" Column="0"/>
            <PointRef Name="TopFinPoint_21" Row="2" Column="1"/>
            <PointRef Name="TopFinPoint_22" Row="2" Column="2"/>
            <PointRef Name="TopFinPoint_23" Row="2" Column="3"/>
            <PointRef Name="TopFinPoint_24" Row="2" Column="4"/>
            <PointRef Name="TopFinPoint_25" Row="2" Column="5"/>
            <PointRef Name="TopFinPoint_26" Row="2" Column="6"/>
            <PointRef Name="TopFinPoint_27" Row="2" Column="7"/>
            <PointRef Name="TopFinPoint_28" Row="2" Column="8"/>
            <PointRef Name="TopFinPoint_29" Row="2" Column="9"/>
            <PointRef Name="TopFinPoint_30" Row="3" Column="0"/>
            <PointRef Name="TopFinPoint_31" Row="3" Column="1"/>
            <PointRef Name="TopFinPoint_32" Row="3" Column="2"/>
            <PointRef Name="TopFinPoint_33" Row="3" Column="3"/>
            <PointRef Name="TopFinPoint_34" Row="3" Column="4"/>
            <PointRef Name="TopFinPoint_35" Row="3" Column="5"/>
            <PointRef Name="TopFinPoint_36" Row="3" Column="6"/>
            <PointRef Name="TopFinPoint_37" Row="3" Column="7"/>
            <PointRef Name="TopFinPoint_38" Row="3" Column="8"/>
            <PointRef Name="TopFinPoint_39" Row="3" Column="9"/>
            <PointRef Name="TopFinPoint_60" Row="4" Column="0"/>
            <PointRef Name="TopFinPoint_61" Row="4" Column="1"/>
            <PointRef Name="TopFinPoint_62" Row="4" Column="2"/>
            <PointRef Name="TopFinPoint_63" Row="4" Column="3"/>
            <PointRef Name="TopFinPoint_64" Row="4" Column="4"/>
            <PointRef Name="TopFinPoint_65" Row="4" Column="5"/>
            <PointRef Name="TopFinPoint_66" Row="4" Column="6"/>
            <PointRef Name="TopFinPoint_67" Row="4" Column="7"/>
            <PointRef Name="TopFinPoint_68" Row="4" Column="8"/>
            <PointRef Name="TopFinPoint_69" Row="4" Column="9"/>
            <PointRef Name="TopFinPoint_50" Row="5" Column="0"/>
            <PointRef Name="TopFinPoint_51" Row="5" Column="1"/>
            <PointRef Name="TopFinPoint_52" Row="5" Column="2"/>
            <PointRef Name="TopFinPoint_53" Row="5" Column="3"/>
            <PointRef Name="TopFinPoint_54" Row="5" Column="4"/>
            <PointRef Name="TopFinPoint_55" Row="5" Column="5"/>
            <PointRef Name="TopFinPoint_56" Row="5" Column="6"/>
            <PointRef Name="TopFinPoint_57" Row="5" Column="7"/>
            <PointRef Name="TopFinPoint_58" Row="5" Column="8"/>
            <PointRef Name="TopFinPoint_59" Row="5" Column="9"/>
            <PointRef Name="TopFinPoint_40" Row="6" Column="0"/>
            <PointRef Name="TopFinPoint_41" Row="6" Column="1"/>
            <PointRef Name="TopFinPoint_42" Row="6" Column="2"/>
            <PointRef Name="TopFinPoint_43" Row="6" Column="3"/>
            <PointRef Name="TopFinPoint_44" Row="6" Column="4"/>
            <PointRef Name="TopFinPoint_45" Row="6" Column="5"/>
            <PointRef Name="TopFinPoint_46" Row="6" Column="6"/>
            <PointRef Name="TopFinPoint_47" Row="6" Column="7"/>
            <PointRef Name="TopFinPoint_48" Row="6" Column="8"/>
            <PointRef Name="TopFinPoint_49" Row="6" Column="9"/>
        </Points>
    </PatchC0>
    <PatchC0 Name="BottomFin" ShowControlPolygon="false" RowSlices="5" ColumnSlices="5" WrapDirection="None">
        <Points>
            <PointRef Name="BottomFinPoint_0" Row="0" Column="0"/>
            <PointRef Name="BottomFinPoint_1" Row="0" Column="1"/>
            <PointRef Name="BottomFinPoint_2" Row="0" Column="2"/>
            <PointRef Name="BottomFinPoint_3" Row="0" Column="3"/>
            <PointRef Name="BottomFinPoint_4" Row="0" Column="4"/>
            <PointRef Name="BottomFinPoint_5" Row="0" Column="5"/>
            <PointRef Name="BottomFinPoint_6" Row="0" Column="6"/>
            <PointRef Name="BottomFinPoint_7" Row="0" Column="7"/>
            <PointRef Name="BottomFinPoint_8" Row="0" Column="8"/>
            <PointRef Name="BottomFinPoint_9" Row="0" Column="9"/>
            <PointRef Name="BottomFinPoint_10" Row="1" Column="0"/>
            <PointRef Name="BottomFinPoint_11" Row="1" Column="1"/>
            <PointRef Name="BottomFinPoint_12" Row="1" Column="2"/>
            <PointRef Name="BottomFinPoint_13" Row="1" Column="3"/>
            <PointRef Name="BottomFinPoint_14" Row="1" Column="4"/>
            <PointRef Name="BottomFinPoint_15" Row="1" Column="5"/>
            <PointRef Name="BottomFinPoint_16" Row="1" Column="6"/>
            <PointRef Name="BottomFinPoint_17" Row="1" Column="7"/>
            <PointRef Name="BottomFinPoint_18" Row="1" Column="8"/>
            <PointRef Name="BottomFinPoint_19" Row="1" Column="9"/>
            <PointRef Name="BottomFinPoint_20" Row="2" Column="0"/>
            <PointRef Name="BottomFinPoint_21" Row="2" Column="1"/>
            <PointRef Name="BottomFinPoint_22" Row="2" Column="2"/>
            <PointRef Name="BottomFinPoint_23" Row="2" Column="3"/>
            <PointRef Name="BottomFinPoint_24" Row="2" Column="4"/>
            <PointRef Name="BottomFinPoint_25" Row="2" Column="5"/>
            <PointRef Name="BottomFinPoint_26" Row="2" Column="6"/>
            <PointRef Name="BottomFinPoint_27" Row="2" Column="7"/>
            <PointRef Name="BottomFinPoint_28" Row="2" Column="8"/>
            <PointRef Name="BottomFinPoint_29" Row="2" Column="9"/>
            <PointRef Name="BottomFinPoint_30" Row="3" Column="0"/>
            <PointRef Name="BottomFinPoint_31" Row="3" Column="1"/>
            <PointRef Name="BottomFinPoint_32" Row="3" Column="2"/>
            <PointRef Name="BottomFinPoint_33" Row="3" Column="3"/>
            <PointRef Name="BottomFinPoint_34" Row="3" Column="4"/>
            <PointRef Name="BottomFinPoint_35" Row="3" Column="5"/>
            <PointRef Name="BottomFinPoint_36" Row="3" Column="6"/>
            <PointRef Name="BottomFinPoint_37" Row="3" Column="7"/>
            <PointRef Name="BottomFinPoint_38" Row="3" Column="8"/>
            <PointRef Name="BottomFinPoint_39" Row="3" Column="9"/>
            <PointRef Name="BottomFinPoint_60" Row="4" Column="0"/>
            <PointRef Name="BottomFinPoint_61" Row="4" Column="1"/>
            <PointRef Name="BottomFinPoint_62" Row="4" Column="2"/>
            <PointRef Name="BottomFinPoint_63" Row="4" Column="3"/>
            <PointRef Name="BottomFinPoint_64" Row="4" Column="4"/>
            <PointRef Name="BottomFinPoint_65" Row="4" Column="5"/>
            <PointRef Name="BottomFinPoint_66" Row="4" Column="6"/>
            <PointRef Name="BottomFinPoint_67" Row="4" Column="7"/>
            <PointRef Name="BottomFinPoint_68" Row="4" Column="8"/>
            <PointRef Name="BottomFinPoint_69" Row="4" Column="9"/>
            <PointRef Name="BottomFinPoint_50" Row="5" Column="0"/>
            <PointRef Name="BottomFinPoint_51" Row="5" Column="1"/>
            <PointRef Name="BottomFinPoint_52" Row="5" Column="2"/>
            <PointRef Name="BottomFinPoint_53" Row="5" Column="3"/>
            <PointRef Name="BottomFinPoint_54" Row="5" Column="4"/>
            <PointRef Name="BottomFinPoint_55" Row="5" Column="5"/>
            <PointRef Name="BottomFinPoint_56" Row="5" Column="6"/>
            <PointRef Name="BottomFinPoint_57" Row="5" Column="7"/>
            <PointRef Name="BottomFinPoint_58" Row="5" Column="8"/>
            <PointRef Name="BottomFinPoint_59" Row="5" Column="9"/>
            <PointRef Name="BottomFinPoint_40" Row="6" Column="0"/>
            <PointRef Name="BottomFinPoint_41" Row="6" Column="1"/>
            <PointRef Name="BottomFinPoint_42" Row="6" Column="2"/>
            <PointRef Name="BottomFinPoint_43" Row="6" Column="3"/>
            <PointRef Name="BottomFinPoint_44" Row="6" Column="4"/>
            <PointRef Name="BottomFinPoint_45" Row="6" Column="5"/>
            <PointRef Name="BottomFinPoint_46" Row="6" Column="6"/>
            <PointRef Name="BottomFinPoint_47" Row="6" Column="7"/>
            <PointRef Name="BottomFinPoint_48" Row="6" Column="8"/>
            <PointRef Name="BottomFinPoint_49" Row="6" Column="9"/>
        </Points>
    </PatchC0>
    <PatchC2 Name="Body" ShowControlPolygon="false" ColumnSlices="5" RowSlices="5" WrapDirection="Column">
        <Points>
            <PointRef Name="KorpusPoint_0" Row="0" Column="0"/>
            <PointRef Name="KorpusPoint_1" Row="0" Column="1"/>
            <PointRef Name="KorpusPoint_2" Row="0" Column="2"/>
            <PointRef Name="KorpusPoint_3" Row="0" Column="3"/>
            <PointRef Name="KorpusPoint_4" Row="0" Column="4"/>
            <PointRef Name="KorpusPoint_5" Row="0" Column="5"/>
            <PointRef Name="KorpusPoint_6" Row="1" Column="0"/>
            <PointRef Name="KorpusPoint_7" Row="1" Column="1"/>
            <PointRef Name="KorpusPoint_8" Row="1" Column="2"/>
            <PointRef Name="KorpusPoint_9" Row="1" Column="3"/>
            <PointRef Name="KorpusPoint_10" Row="1" Column="4"/>
            <PointRef Name="KorpusPoint_11" Row="1" Column="5"/>
            <PointRef Name="KorpusPoint_12" Row="2" Column="0"/>
            <PointRef Name="KorpusPoint_13" Row="2" Column="1"/>
            <PointRef Name="KorpusPoint_14" Row="2" Column="2"/>
            <PointRef Name="KorpusPoint_15" Row="2" Column="3"/>
            <PointRef Name="KorpusPoint_16" Row="2" Column="4"/>
            <PointRef Name="KorpusPoint_17" Row="2" Column="5"/>
            <PointRef Name="KorpusPoint_18" Row="3" Column="0"/>
            <PointRef Name="KorpusPoint_19" Row="3" Column="1"/>
            <PointRef Name="KorpusPoint_20" Row="3" Column="2"/>
            <PointRef Name="KorpusPoint_21" Row="3" Column="3"/>
            <PointRef Name="KorpusPoint_22" Row="3" Column="4"/>
            <PointRef Name="KorpusPoint_23" Row="3" Column="5"/>
            <PointRef Name="KorpusPoint_24" Row="4" Column="0"/>
            <PointRef Name="KorpusPoint_25" Row="4" Column="1"/>
            <PointRef Name="KorpusPoint_26" Row="4" Column="2"/>
            <PointRef Name="KorpusPoint_27" Row="4" Column="3"/>
            <PointRef Name="KorpusPoint_28" Row="4" Column="4"/>
            <PointRef Name="KorpusPoint_29" Row="4" Column="5"/>
            <PointRef Name="KorpusPoint_30" Row="5" Column="0"/>
            <PointRef Name="KorpusPoint_31" Row="5" Column="1"/>
            <PointRef Name="KorpusPoint_32" Row="5" Column="2"/>
            <PointRef Name="KorpusPoint_33" Row="5" Column="3"/>
            <PointRef Name="KorpusPoint_34" Row="5" Column="4"/>
            <PointRef Name="KorpusPoint_35" Row="5" Column="5"/>
            <PointRef Name="KorpusPoint_36" Row="6" Column="0"/>
            <PointRef Name="KorpusPoint_37" Row="6" Column="1"/>
            <PointRef Name="KorpusPoint_38" Row="6" Column="2"/>
            <PointRef Name="KorpusPoint_39" Row="6" Column="3"/>
            <PointRef Name="KorpusPoint_40" Row="6" Column="4"/>
            <PointRef Name="KorpusPoint_41" Row="6" Column="5"/>
        </Points>
    </PatchC2>
    <PatchC2 Name="Loop" ShowControlPolygon="false" ColumnSlices="5" RowSlices="5" WrapDirection="Column">
        <Points>
            <PointRef Name="LoopPoint_0" Row="0" Column="0"/>
            <PointRef Name="LoopPoint_1" Row="0" Column="1"/>
            <PointRef Name="LoopPoint_2" Row="0" Column="2"/>
            <PointRef Name="LoopPoint_3" Row="0" Column="3"/>
            <PointRef Name="LoopPoint_4" Row="1" Column="0"/>
            <PointRef Name="LoopPoint_5" Row="1" Column="1"/>
            <PointRef Name="LoopPoint_6" Row="1" Column="2"/>
            <PointRef Name="LoopPoint_7" Row="1" Column="3"/>
            <PointRef Name="LoopPoint_8" Row="2" Column="0"/>
            <PointRef Name="LoopPoint_9" Row="2" Column="1"/>
            <PointRef Name="LoopPoint_10" Row="2" Column="2"/>
            <PointRef Name="LoopPoint_11" Row="2" Column="3"/>
            <PointRef Name="LoopPoint_12" Row="3" Column="0"/>
            <PointRef Name="LoopPoint_13" Row="3" Column="1"/>
            <PointRef Name="LoopPoint_14" Row="3" Column="2"/>
            <PointRef Name="LoopPoint_15" Row="3" Column="3"/>
            <PointRef Name="LoopPoint_16" Row="4" Column="0"/>
            <PointRef Name="LoopPoint_17" Row="4" Column="1"/>
            <PointRef Name="LoopPoint_18" Row="4" Column="2"/>
            <PointRef Name="LoopPoint_19" Row="4" Column="3"/>
            <PointRef Name="LoopPoint_20" Row="5" Column="0"/>
            <PointRef Name="LoopPoint_21" Row="5" Column="1"/>
            <PointRef Name="LoopPoint_22" Row="5" Column="2"/>
            <PointRef Name="LoopPoint_23" Row="5" Column="3"/>
            <PointRef Name="LoopPoint_24" Row="6" Column="0"/>
            <PointRef Name="LoopPoint_25" Row="6" Column="1"/>
            <PointRef Name="LoopPoint_26" Row="6" Column="2"/>
            <PointRef Name="LoopPoint_27" Row="6" Column="3"/>
        </Points>
    </PatchC2>
    <PatchC2 Name="Tail" ShowControlPolygon="false" ColumnSlices="5" RowSlices="5" WrapDirection="Column">
        <Points>
            <PointRef Name="TailPoint_0" Row="0" Column="0"/>
            <PointRef Name="TailPoint_1" Row="0" Column="1"/>
            <PointRef Name="TailPoint_2" Row="0" Column="2"/>
            <PointRef Name="TailPoint_3" Row="0" Column="3"/>
            <PointRef Name="TailPoint_4" Row="0" Column="4"/>
            <PointRef Name="TailPoint_5" Row="0" Column="5"/>
            <PointRef Name="TailPoint_6" Row="1" Column="0"/>
            <PointRef Name="TailPoint_7" Row="1" Column="1"/>
            <PointRef Name="TailPoint_8" Row="1" Column="2"/>
            <PointRef Name="TailPoint_9" Row="1" Column="3"/>
            <PointRef Name="TailPoint_10" Row="1" Column="4"/>
            <PointRef Name="TailPoint_11" Row="1" Column="5"/>
            <PointRef Name="TailPoint_12" Row="2" Column="0"/>
            <PointRef Name="TailPoint_13" Row="2" Column="1"/>
            <PointRef Name="TailPoint_14" Row="2" Column="2"/>
            <PointRef Name="TailPoint_15" Row="2" Column="3"/>
            <PointRef Name="TailPoint_16" Row="2" Column="4"/>
            <PointRef Name="TailPoint_17" Row="2" Column="5"/>
            <PointRef Name="TailPoint_18" Row="3" Column="0"/>
            <PointRef Name="TailPoint_19" Row="3" Column="1"/>
            <PointRef Name="TailPoint_20" Row="3" Column="2"/>
            <PointRef Name="TailPoint_21" Row="3" Column="3"/>
            <PointRef Name="TailPoint_22" Row="3" Column="4"/>
            <PointRef Name="TailPoint_23" Row="3" Column="5"/>
            <PointRef Name="TailPoint_24" Row="4" Column="0"/>
            <PointRef Name="TailPoint_25" Row="4" Column="1"/>
            <PointRef Name="TailPoint_26" Row="4" Column="2"/>
            <PointRef Name="TailPoint_27" Row="4" Column="3"/>
            <PointRef Name="TailPoint_28" Row="4" Column="4"/>
            <PointRef Name="TailPoint_29" Row="4" Column="5"/>
            <PointRef Name="TailPoint_30" Row="5" Column="0"/>
            <PointRef Name="TailPoint_31" Row="5" Column="1"/>
            <PointRef Name="TailPoint_32" Row="5" Column="2"/>
            <PointRef Name="TailPoint_33" Row="5" Column="3"/>
            <PointRef Name="TailPoint_34" Row="5" Column="4"/>
            <PointRef Name="TailPoint_35" Row="5" Column="5"/>
            <PointRef Name="TailPoint_36" Row="6" Column="0"/>
            <PointRef Name="TailPoint_37" Row="6" Column="1"/>
            <PointRef Name="TailPoint_38" Row="6" Column="2"/>
            <PointRef Name="TailPoint_39" Row="6" Column="3"/>
            <PointRef Name="TailPoint_40" Row="6" Column="4"/>
            <PointRef Name="TailPoint_41" Row="6" Column="5"/>
            <PointRef Name="TailPoint_42" Row="7" Column="0"/>
            <PointRef Name="TailPoint_43" Row="7" Column="1"/>
            <PointRef Name="TailPoint_44" Row="7" Column="2"/>
            <PointRef Name="TailPoint_45" Row="7" Column="3"/>
            <PointRef Name="TailPoint_46" Row="7" Column="4"/>
            <PointRef Name="TailPoint_47" Row="7" Column="5"/>
            <PointRef Name="TailPoint_48" Row="8" Column="0"/>
            <PointRef Name="TailPoint_49" Row="8" Column="1"/>
            <PointRef Name="TailPoint_50" Row="8" Column="2"/>
            <PointRef Name="TailPoint_51" Row="8" Column="3"/>
            <PointRef Name="TailPoint_52" Row="8" Column="4"/>
            <PointRef Name="TailPoint_53" Row="8" Column="5"/>
        </Points>
    </PatchC2>
</Scene>
